KuaileDeLinuxMinglingxingFix1/README.md
KuaileDeLinuxMinglingxingFix1/__init__.py
KuaileDeLinuxMinglingxingFix1/__main__.py
KuaileDeLinuxMinglingxingFix1/file.epub
KuaileDeLinuxMinglingxingFix1/index.html
KuaileDeLinuxMinglingxingFix1/css/__init__.py
KuaileDeLinuxMinglingxingFix1/css/annotations.css
KuaileDeLinuxMinglingxingFix1/css/main.css
KuaileDeLinuxMinglingxingFix1/css/normalize.css
KuaileDeLinuxMinglingxingFix1/css/popup.css
KuaileDeLinuxMinglingxingFix1/font/__init__.py
KuaileDeLinuxMinglingxingFix1/font/fontello.eot
KuaileDeLinuxMinglingxingFix1/font/fontello.svg
KuaileDeLinuxMinglingxingFix1/font/fontello.ttf
KuaileDeLinuxMinglingxingFix1/font/fontello.woff
KuaileDeLinuxMinglingxingFix1/img/__init__.py
KuaileDeLinuxMinglingxingFix1/img/annotator-glyph-sprite.png
KuaileDeLinuxMinglingxingFix1/img/annotator-icon-sprite.png
KuaileDeLinuxMinglingxingFix1/img/apple-touch-icon.png
KuaileDeLinuxMinglingxingFix1/img/cancelfullscreen.png
KuaileDeLinuxMinglingxingFix1/img/close.png
KuaileDeLinuxMinglingxingFix1/img/fullscreen.png
KuaileDeLinuxMinglingxingFix1/img/loader.gif
KuaileDeLinuxMinglingxingFix1/img/menu-icon.png
KuaileDeLinuxMinglingxingFix1/img/save.png
KuaileDeLinuxMinglingxingFix1/img/saved.png
KuaileDeLinuxMinglingxingFix1/img/settings-s.png
KuaileDeLinuxMinglingxingFix1/img/settings.png
KuaileDeLinuxMinglingxingFix1/img/star.png
KuaileDeLinuxMinglingxingFix1/js/__init__.py
KuaileDeLinuxMinglingxingFix1/js/epub.js
KuaileDeLinuxMinglingxingFix1/js/epub.min.js
KuaileDeLinuxMinglingxingFix1/js/epub.min.map
KuaileDeLinuxMinglingxingFix1/js/hooks.min.js
KuaileDeLinuxMinglingxingFix1/js/hooks.min.map
KuaileDeLinuxMinglingxingFix1/js/reader.js
KuaileDeLinuxMinglingxingFix1/js/reader.js.map
KuaileDeLinuxMinglingxingFix1/js/reader.min.js
KuaileDeLinuxMinglingxingFix1/js/reader.min.map
KuaileDeLinuxMinglingxingFix1/js/hooks/__init__.py
KuaileDeLinuxMinglingxingFix1/js/hooks/extensions/__init__.py
KuaileDeLinuxMinglingxingFix1/js/hooks/extensions/highlight.js
kuaile_de_linux_minglingxing_fix1-2025.3.25.1.dist-info/METADATA
kuaile_de_linux_minglingxing_fix1-2025.3.25.1.dist-info/WHEEL
kuaile_de_linux_minglingxing_fix1-2025.3.25.1.dist-info/entry_points.txt
kuaile_de_linux_minglingxing_fix1-2025.3.25.1.dist-info/top_level.txt
kuaile_de_linux_minglingxing_fix1-2025.3.25.1.dist-info/RECORD
